{
	"ulid": "01HBSQYD7M7ZS5KSCD98KHEHCB",
	"minTime": 1696205477659,
	"maxTime": 1696269600000,
	"stats": {
		"numSamples": 567548,
		"numSeries": 496,
		"numChunks": 7037
	},
	"compaction": {
		"level": 3,
		"sources": [
			"01HBQ7CK0Z7E4B3X87CMSJSTFP",
			"01HBQCGWMRZ5DW5E6WG6YNJ8SG",
			"01HBQJZN4FYK5A6FVA4N197YMC",
			"01HBQSZ2JVNXRM3YP1FDR804ZP",
			"01HBR2P1QY1KEDRHE99YFYHDDX",
			"01HBR7NQQ9Q36E631XN5P9WJ18",
			"01HBREFG0ZE95Z4S9R91S8X4TK",
			"01HBS18KKPE43V705T62SQFT7P",
			"01HBS18M389VBZ88QH1P4A6MKW"
		],
		"parents": [
			{
				"ulid": "01HBR2P24R1S0N9A1W090R4KPV",
				"minTime": 1696205477659,
				"maxTime": 1696226400000
			},
			{
				"ulid": "01HBS18MCMZ27E78GSFJP2N3F8",
				"minTime": 1696226403849,
				"maxTime": 1696248000000
			},
			{
				"ulid": "01HBSQYCYF9G38G68TYVPDRBJX",
				"minTime": 1696248015277,
				"maxTime": 1696269600000
			}
		]
	},
	"version": 1
}